[
    {
        "id": "advertise_with_us",
        "pagename": "Advertise with Us",
        "elements": [
            {
                "id": "container_1",
                "elements": [
                    {
                        "image": "/images/commercial/advertise-with-us/container-1/cover.jpg",
                        "card": {
                            "title": "IMS PRASAR",
                            "subtitle": "Let us Do Incredible Things",
                            "content": "<p>Audiences who connect with our brands on all our channels are highly engaged and eager to act. They actively seek inspiration and ideas from professionals and brands they admire. Make an effect in the world of distraction. With the attention economy contracting, building consumer trust is critical to breaking through the noise.<br/><br/> Our multidisciplinary Digital Ad Innovation team combines the art of storytelling with the science of smart audience targeting to offer meaningful engagement at scale in a trusted, brand-safe environment. We look forward to sharing that inspiration with you.</p>"
                        }
                    }
                ]
            },
            {
                "id": "container_2",
                "elements": [
                    {
                        "image": "/images/commercial/advertise-with-us/container-2/cover.jpg",
                        "card": {
                            "title": "ABOUT US",
                            "subtitle": "India celebrates Exploration",
                            "content": "<p>Indian Media Syndicate strives to be the global leader in Exploration, Scientific Communications, Real Life Entertainment, serving passionate Explorers around the world with scientific journalism that inspires, informs and entertains.<br /><br /> This is an Indian family of informational, educational and entertainment-oriented Television, Applications and Websites offering value to how Education is developed and accessed by Indic Societies.</p>"
                        }
                    }
                ]
            },
            {
                "id": "container_3",
                "elements": [
                    {
                        "title": "INDIAN MEDIA SYNDICATE MEMBERSHIP",
                        "subtitle": "The Greatest Event in Indian Broadcasting",
                        "membershipcard": [
                            {
                                "title": "Advertisement Enquiry",
                                "inputfield": [
                                    {
                                        "label": "Name",
                                        "type": "text",
                                        "id": "name"
                                    },
                                    {
                                        "label": "Official email",
                                        "type": "email",
                                        "id": "email"
                                    }
                                ],
                                "optionfield": [
                                    {
                                        "label": "Requirement",
                                        "type": "select",
                                        "id": "Requirement",
                                        "option": [
                                            "Requirement","10", "20", "30", "40", "50", "60", "70", "80", "90", "100+"
                                        ]
                                    },
                                    {
                                        "label": "Region",
                                        "type": "select",
                                        "id": "region",
                                        "option": [
                                            "Region","Mumbai", "Chennai", "Delhi", "Kanpur", "Prayagraj"
                                        ]
                                    }
                                ],
                                "buttontext": "Next"
                            },
                            {
                                "title": "PRASAR Techonology",
                                "buttons": [
                                    {
                                        "text": "+ Ad Intelligence",
                                        "link": "#"
                                    },
                                    {
                                        "text": "+ Channels",
                                        "link": "#"
                                    },
                                    {
                                        "text": "See All",
                                        "link": "#"
                                    }
                                ]
                            }
                        ],
                        "cards": [
                            {
                                "id": 1,
                                "button": "DISCOVER",
                                "image": "/images/commercial/advertise-with-us/container-3/cover.jpg", 
                                "title": "IMS",
                                "subtitle": "PRASAR",
                                "content": "Precious Members of the Indian Media Syndicate"
                            },
                            {
                                "id": 2,
                                "button": "CHECK",
                                "image": "/images/commercial/advertise-with-us/container-3/cover.jpg",
                                "title": "Advert",
                                "subtitle": "POLICY",
                                "content": "Guidelines for IMS title Productions (Procedural)"
                            },
                            {
                                "id": 3,
                                "button": "CHECK",
                                "image": "/images/commercial/advertise-with-us/container-3/cover.jpg",
                                "title": "PRASAR",
                                "subtitle": "MONETIZATION",
                                "content": "Guidelines for IMS production partners and terms of cooperation"
                            }
                        ]
                    }
                ]
            },
            {
                "id": "container_4",
                "elements": [
                    {
                        "image": "/images/commercial/investors/container-4/cover.jpg",
                        "title": "IMS Explorers",
                        "subtitle": "Changemakers<br /> and Innovators",
                        "buttontext": "APPLY"
                    }
                ]
            }
        ]
    },
    {
        "id": "investors",
        "pagename": "Investors",
        "elements": [
            {
                "id": "container_1",
                "elements": [
                    {
                        "image": "/images/commercial/investors/container-1/cover.jpg",
                        "card": {
                            "title": "WHAT WE DO",
                            "subtitle": "India celebrates Exploration",
                            "content": "<p>Indian Media Syndicate strives to be the global leader in Exploration, Scientific Communications, Real Life Entertainment, serving passionate Explorers around the world with scientific journalism that inspires, informs and entertains.<br /><br /> This is an Indian family of informational, educational and entertainment-oriented Television, Applications and Websites offering value to how Education is developed and accessed by Indic Societies.</p>"
                        }
                    }
                ]
            },
            {
                "id": "container_2",
                "elements": [
                    {
                        "heading": {
                            "title": "OUR MISSION",
                            "subtitle": "To Revolutionize Indian Media",
                            "content": "<p>By making every Information, every Discovery, every Invention, every Challenge accessible to every person in the India pacific Region</p>"
                        }
                    },
                    {
                        "images": {
                            "imageTop": "/images/commercial/investors/container-2/image-top.jpg",
                            "imageBottom": "/images/commercial/investors/container-2/image-bottom.jpg"
                        }
                    },
                    {
                        "card": {
                            "subtitle": "Making Knowledge Accessible to All.",
                            "content": "<p>Each control has been designed for multiple use, several administrators will be able to assign content remotely from their mobile phones, without any worries.</p>",
                            "buttontext": "VIEW MORE"
                        }
                    }
                ]
            },
            {
                "id": "container_3",
                "elements": [
                    {
                        "cards": [
                            {
                                "id": 1,
                                "count": 265,
                                "cardtitle": "Conserved Species",
                                "cardcontent": "Curabitur blandit tempus porttitor. Sed posuere consectetur est at lobortis."
                            },
                            {
                                "id": 2,
                                "count": 265,
                                "cardtitle": "Conserved Species",
                                "cardcontent": "Curabitur blandit tempus porttitor. Sed posuere consectetur est at lobortis."
                            },
                            {
                                "id": 3,
                                "count": 265,
                                "cardtitle": "Conserved Species",
                                "cardcontent": "Curabitur blandit tempus porttitor. Sed posuere consectetur est at lobortis."
                            }
                        ]
                    },
                    {
                        "image": "/images/commercial/investors/container-3/cover.jpg",
                        "card": {
                            "title": "ABOUT US",
                            "subtitle": "India celebrates Exploration",
                            "content": "<p>Indian Media Syndicate endeavors to be the global leader in Exploration, Scientific Communications, Real Life Entertainment, serving passionate Explorers around the world generating scientific journalism that inspires, informs and entertains.<br /> <br />This is an Indian family of informational, educational and entertainment-oriented Television, Applications and Websites offering value to how Education is developed and accessed by the world.</p>"
                        }
                    }
                ]
            },
            {
                "id": "container_4",
                "elements": [
                    {
                        "image": "/images/commercial/investors/container-4/cover.jpg",
                        "title": "IMS Explorers",
                        "subtitle": "Changemakers<br /> and Innovators",
                        "buttontext": "APPLY"
                    }
                ]
            }
        ]
    },
    {
        "id": "sustainability_statement",
        "pagename": "Sustainability Statement",
        "elements": [
            {
                "id": "container_1",
                "elements": [
                    {
                        "image": "/images/commercial/sustainability-statement/container-1/cover.jpg",
                        "card": {
                            "title": "WHAT WE DO",
                            "subtitle": "India celebrates Exploration",
                            "content": "<p>Indian Media Syndicate strives to be the global leader in Exploration, Scientific Communications, Real Life Entertainment, serving passionate Explorers around the world with scientific journalism that inspires, informs and entertains.<br /><br /> This is an Indian family of informational, educational and entertainment-oriented Television, Applications and Websites offering value to how Education is developed and accessed by Indic Societies.</p>"
                        }
                    }
                ]
            },
            {
                "id": "container_2",
                "elements": [
                    {
                        "heading": {
                            "title": "OUR MISSION",
                            "subtitle": "To Revolutionize Indian Media",
                            "content": "<p>By making every Information, every Discovery, every Invention, every Challenge accessible to every person in the India pacific Region</p>"
                        }
                    },
                    {
                        "images": {
                            "imageTop": "/images/commercial/sustainability-statement/container-2/image-top.jpg",
                            "imageBottom": "/images/commercial/sustainability-statement/container-2/image-bottom.jpg"
                        }
                    },
                    {
                        "card": {
                            "subtitle": "Making Knowledge Accessible to All.",
                            "content": "<p>Each control has been designed for multiple use, several administrators will be able to assign content remotely from their mobile phones, without any worries.</p>",
                            "buttontext": "VIEW MORE"
                        }
                    }
                ]
            },
            {
                "id": "container_3",
                "elements": [
                    {
                        "cards": [
                            {
                                "id": 1,
                                "count": 265,
                                "cardtitle": "Conserved Species",
                                "cardcontent": "Curabitur blandit tempus porttitor. Sed posuere consectetur est at lobortis."
                            },
                            {
                                "id": 2,
                                "count": 265,
                                "cardtitle": "Conserved Species",
                                "cardcontent": "Curabitur blandit tempus porttitor. Sed posuere consectetur est at lobortis."
                            },
                            {
                                "id": 3,
                                "count": 265,
                                "cardtitle": "Conserved Species",
                                "cardcontent": "Curabitur blandit tempus porttitor. Sed posuere consectetur est at lobortis."
                            }
                        ]
                    },
                    {
                        "image": "/images/commercial/sustainability-statement/container-3/cover.jpg",
                        "card": {
                            "title": "ABOUT US",
                            "subtitle": "India celebrates Exploration",
                            "content": "<p>Indian Media Syndicate endeavors to be the global leader in Exploration, Scientific Communications, Real Life Entertainment, serving passionate Explorers around the world generating scientific journalism that inspires, informs and entertains.<br /> <br />This is an Indian family of informational, educational and entertainment-oriented Television, Applications and Websites offering value to how Education is developed and accessed by the world.</p>"
                        }
                    }
                ]
            },
            {
                "id": "container_4",
                "elements": [
                    {
                        "image": "/images/commercial/sustainability-statement/container-4/cover.jpg",
                        "title": "IMS Explorers",
                        "subtitle": "Changemakers<br /> and Innovators",
                        "buttontext": "APPLY"
                    }
                ]
            }
        ]
    }
]